latent_calendar/__init__.py
latent_calendar/const.py
latent_calendar/extensions.py
latent_calendar/generate.py
latent_calendar/py.typed
latent_calendar/transformers.py
latent_calendar/vocab.py
latent_calendar/datasets/__init__.py
latent_calendar/model/__init__.py
latent_calendar/model/latent_calendar.py
latent_calendar/model/utils.py
latent_calendar/plot/__init__.py
latent_calendar/plot/colors.py
latent_calendar/plot/config.py
latent_calendar/plot/elements.py
latent_calendar/plot/grid_settings.py
latent_calendar/plot/iterate.py
latent_calendar/plot/core/__init__.py
latent_calendar/plot/core/calendar.py
latent_calendar/plot/core/model.py
latent_calendar/segments/__init__.py
latent_calendar/segments/convolution.py
latent_calendar/segments/hand_picked.py
latent_calendar-1.7.0.dist-info/METADATA
latent_calendar-1.7.0.dist-info/WHEEL
latent_calendar-1.7.0.dist-info/licenses/LICENSE
latent_calendar-1.7.0.dist-info/RECORD
