Metadata-Version: 2.4
Name: latent-calendar
Version: 1.7.0
Summary: Analyzing and modeling weekly calendar distributions using latent components
Project-URL: Homepage, https://williambdean.github.io/latent-calendar/
Project-URL: Repository, https://github.com/williambdean/latent-calendar/
Project-URL: Documentation, https://williambdean.github.io/latent-calendar/
Author-email: Will Dean <wd60622@gmail.com>
License-File: LICENSE
Classifier: Intended Audience :: Developers
Classifier: Intended Audience :: Science/Research
Classifier: Operating System :: MacOS
Classifier: Operating System :: Microsoft :: Windows
Classifier: Operating System :: POSIX
Classifier: Operating System :: POSIX :: Linux
Classifier: Operating System :: Unix
Classifier: Programming Language :: Python
Classifier: Programming Language :: Python :: 3
Classifier: Programming Language :: Python :: 3.10
Classifier: Programming Language :: Python :: 3.11
Classifier: Programming Language :: Python :: 3.12
Classifier: Programming Language :: Python :: 3.13
Classifier: Topic :: Scientific/Engineering
Classifier: Topic :: Software Development :: Libraries
Requires-Python: <4.0,>=3.10
Requires-Dist: conjugate-models>=0.9.0
Requires-Dist: matplotlib>=3.5.0
Requires-Dist: narwhals>=1.44.0
Requires-Dist: pandas>=1.0.0
Requires-Dist: scikit-learn>=1.0.0
Provides-Extra: pymc
Requires-Dist: pymc>=5.0.0; extra == 'pymc'
